{"scope":{"_notifyingListeners":false,"_scopeListeners":[],"_eventProcessors":[],"_breadcrumbs":[{"timestamp":1720369267.128,"category":"console","level":"log","message":"splashScreen: SPLASH_SCREEN_READY"},{"timestamp":1720369267.129,"category":"console","level":"log","message":"splashScreen.webContentsSend: SPLASH_SCREEN_QUOTE SPLASH_SCREEN_QUOTE [ 'Hold Tight — Loading Discord' ]"},{"timestamp":1720369267.13,"category":"electron","message":"window.show","type":"ui","data":{"id":1,"url":"app:///app_bootstrap/splash/index.html"}},{"timestamp":1720369267.131,"category":"console","level":"log","message":"2024-07-07T16:21:07.130Z [Modules] No updates to install"},{"timestamp":1720369267.131,"category":"console","level":"log","message":"splashScreen: no-pending-updates"},{"timestamp":1720369267.131,"category":"console","level":"log","message":"2024-07-07T16:21:07.131Z [Modules] Host is up to date."},{"timestamp":1720369267.131,"category":"console","level":"log","message":"2024-07-07T16:21:07.131Z [Modules] Checking for module updates at https://discord.com/api/modules/stable/versions.json"},{"timestamp":1720369267.132,"category":"console","level":"log","message":"splashScreen: checking-for-updates"},{"timestamp":1720369267.132,"category":"console","level":"log","message":"splashScreen.updateSplashState checking-for-updates checking-for-updates {}"},{"timestamp":1720369267.132,"category":"console","level":"log","message":"splashScreen.webContentsSend: SPLASH_UPDATE_STATE SPLASH_UPDATE_STATE [ { status: 'checking-for-updates' } ]"},{"timestamp":1720369267.137,"category":"electron","message":"window.focus","type":"ui","data":{"id":1,"url":"app:///app_bootstrap/splash/index.html"}},{"timestamp":1720369267.138,"category":"electron","message":"app.browser-window-focus","type":"ui"},{"timestamp":1720369267.147,"category":"electron","message":"renderer.dom-ready","type":"ui","data":{"id":1,"url":"app:///app_bootstrap/splash/index.html"}},{"timestamp":1720369267.158,"category":"console","level":"log","message":"blackbox: 2024-07-07T16:21:07.158Z 4 ✅ webContents.did-finish-load web1"},{"timestamp":1720369267.402,"type":"http","category":"electron.net","data":{"url":"https://discord.com/api/modules/stable/versions.json?host_version=0.0.58&platform=linux&_=5734564","method":"GET","status_code":200}},{"timestamp":1720369267.404,"category":"console","level":"log","message":"2024-07-07T16:21:07.404Z [Modules] No module updates available."},{"timestamp":1720369267.404,"category":"console","level":"log","message":"splashScreen: update-check-finished true 0 false"},{"timestamp":1720369267.404,"category":"console","level":"log","message":"CDM completed with status (old updater): [{\"id\":\"oimompecagnajdejgnnjijobebaeigek\",\"status\":\"new\",\"title\":\"Widevine Content Decryption Module\",\"version\":\"4.10.2710.0\"}]"},{"timestamp":1720369267.405,"category":"console","level":"log","message":"splashScreen.launchMainWindow: false"},{"timestamp":1720369267.447,"category":"electron","message":"powerMonitor.newListener","type":"ui"},{"timestamp":1720369267.447,"category":"electron","message":"powerMonitor.newListener","type":"ui"},{"timestamp":1720369267.447,"category":"electron","message":"powerMonitor.newListener","type":"ui"},{"timestamp":1720369267.447,"category":"electron","message":"powerMonitor.newListener","type":"ui"},{"timestamp":1720369267.447,"category":"electron","message":"powerMonitor.newListener","type":"ui"},{"timestamp":1720369267.456,"category":"electron","message":"app.web-contents-created","type":"ui"},{"timestamp":1720369267.459,"category":"electron","message":"app.browser-window-created","type":"ui"},{"timestamp":1720369267.46,"category":"console","level":"log","message":"Optional module ./ElectronTestRpc was not included."},{"timestamp":1720369267.469,"category":"console","level":"log","message":"splashScreen.updateSplashState launching launching {}"},{"timestamp":1720369267.469,"category":"console","level":"log","message":"splashScreen.webContentsSend: SPLASH_UPDATE_STATE SPLASH_UPDATE_STATE [ { status: 'launching' } ]"},{"timestamp":1720369267.47,"category":"console","level":"log","message":"blackbox: 2024-07-07T16:21:07.470Z 5 ✅ webContents.created web2 \"\""},{"timestamp":1720369267.483,"category":"console","level":"log","message":"blackbox: 2024-07-07T16:21:07.483Z 6 ✅ window.created win2 \"Discord\""},{"timestamp":1720369268.528,"category":"console","data":{"arguments":["Initializing voice engine with audio subsystem: false"],"logger":"console"},"level":"log","message":"Initializing voice engine with audio subsystem: false"},{"timestamp":1720369268.635,"category":"console","level":"log","message":"legacyModuleUpdater: installed-module discord_krisp 1 1 true"},{"timestamp":1720369268.642,"category":"console","level":"log","message":"legacyModuleUpdater: installed-module discord_game_utils 1 1 true"},{"timestamp":1720369268.794,"category":"console","level":"log","message":"mainScreen.UpdaterEvents: UPDATER_HISTORY_QUERY_AND_TRUNCATE"},{"timestamp":1720369268.831,"category":"electron","message":"renderer.dom-ready","type":"ui","data":{"id":2,"url":"https://discord.com/app?_=1720369267444"}},{"timestamp":1720369268.842,"category":"console","data":{"arguments":["Initializing krisp module"],"logger":"console"},"level":"info","message":"Initializing krisp module"},{"timestamp":1720369269.337,"category":"console","level":"log","message":"mainScreen.on(did-finish-load) false false"},{"timestamp":1720369269.338,"category":"console","level":"log","message":"splashScreen.pageReady"},{"timestamp":1720369269.339,"category":"electron","message":"window.show","type":"ui","data":{"id":2,"url":"https://discord.com/app?_=1720369267444"}},{"timestamp":1720369269.339,"category":"console","level":"log","message":"blackbox: 2024-07-07T16:21:09.339Z 7 ✅ webContents.did-finish-load web2"},{"timestamp":1720369269.35,"category":"electron","message":"window.blur","type":"ui","data":{"id":1,"url":"app:///app_bootstrap/splash/index.html"}},{"timestamp":1720369269.35,"category":"electron","message":"app.browser-window-blur","type":"ui"},{"timestamp":1720369269.35,"category":"electron","message":"window.focus","type":"ui","data":{"id":2,"url":"https://discord.com/app?_=1720369267444"}},{"timestamp":1720369269.35,"category":"electron","message":"app.browser-window-focus","type":"ui"},{"timestamp":1720369269.48,"category":"electron","message":"window.hide","type":"ui","data":{"id":1,"url":"app:///app_bootstrap/splash/index.html"}},{"timestamp":1720369269.48,"category":"electron","message":"window.close","type":"ui","data":{"id":1,"url":"app:///app_bootstrap/splash/index.html"}},{"timestamp":1720369269.48,"category":"console","level":"log","message":"blackbox: 2024-07-07T16:21:09.480Z 8 window.close win1"},{"timestamp":1720369269.49,"category":"console","level":"log","message":"mainScreen.UpdaterEvents: UPDATER_HISTORY_QUERY_AND_TRUNCATE"},{"timestamp":1720369269.492,"category":"electron","message":"renderer.destroyed","type":"ui","data":{"id":1,"url":"app:///app_bootstrap/splash/index.html"}},{"timestamp":1720369269.492,"category":"electron","message":"window.closed","type":"ui","data":{"id":1,"url":"app:///app_bootstrap/splash/index.html"}},{"timestamp":1720369269.51,"category":"console","level":"log","message":"mainScreen.UpdaterEvents: UPDATER_HISTORY_QUERY_AND_TRUNCATE"},{"timestamp":1720369269.524,"category":"console","level":"log","message":"blackbox: 2024-07-07T16:21:09.524Z 9 webContents.destroyed web1"},{"timestamp":1720369269.533,"category":"console","level":"log","message":"blackbox: 2024-07-07T16:21:09.533Z 10 window.closed win1"},{"timestamp":1720369269.852,"category":"console","level":"error","message":"Error occurred in handler for 'bd-get-accent-color': TypeError: e.systemPreferences.getAccentColor is not a function\n    at D (/home/noelle/.config/BetterDiscord/data/betterdiscord.asar/injector.js:1:6662)\n    at WebContents.<anonymous> (node:electron/js2c/browser_init:2:84019)\n    at WebContents.emit (node:events:519:28)\n    at WebContents.emit (node:domain:488:12)\n    at emitter.emit (/nix/store/f3x3snsnjnfzg12g7586syg5cyn8sgph-discord-0.0.58/opt/Discord/resources/app.asar/node_modules/@sentry/electron/main/integrations/electron-breadcrumbs.js:116:20)"},{"timestamp":1720369270.655,"category":"console","data":{"arguments":["Initializing voice engine with audio subsystem: false"],"logger":"console"},"level":"log","message":"Initializing voice engine with audio subsystem: false"},{"timestamp":1720369270.704,"category":"console","level":"log","message":"legacyModuleUpdater: installed-module discord_krisp 1 1 true"},{"timestamp":1720369270.709,"category":"console","level":"log","message":"legacyModuleUpdater: installed-module discord_game_utils 1 1 true"},{"timestamp":1720369270.771,"category":"console","level":"log","message":"mainScreen.UpdaterEvents: UPDATER_HISTORY_QUERY_AND_TRUNCATE"},{"timestamp":1720369271.084,"category":"electron","message":"renderer.dom-ready","type":"ui","data":{"id":2,"url":"https://discord.com/app?_=1720369267444"}},{"timestamp":1720369271.092,"category":"console","level":"log","message":"mainScreen.UpdaterEvents: UPDATER_HISTORY_QUERY_AND_TRUNCATE"},{"timestamp":1720369271.096,"category":"console","data":{"arguments":["Initializing krisp module"],"logger":"console"},"level":"info","message":"Initializing krisp module"},{"timestamp":1720369271.671,"category":"console","level":"log","message":"mainScreen.on(did-finish-load) false true"},{"timestamp":1720369271.673,"category":"console","level":"log","message":"splashScreen.pageReady"},{"timestamp":1720369271.673,"category":"console","level":"error","message":"splashScreen.destroySplash: splashWindow is null."},{"timestamp":1720369271.673,"category":"console","level":"log","message":"blackbox: 2024-07-07T16:21:11.673Z 11 ✅ webContents.did-finish-load web2"},{"timestamp":1720369271.757,"category":"console","level":"log","message":"mainScreen.UpdaterEvents: UPDATER_HISTORY_QUERY_AND_TRUNCATE"},{"timestamp":1720369272.201,"category":"console","level":"error","message":"Error occurred in handler for 'bd-get-accent-color': TypeError: e.systemPreferences.getAccentColor is not a function\n    at D (/home/noelle/.config/BetterDiscord/data/betterdiscord.asar/injector.js:1:6662)\n    at WebContents.<anonymous> (node:electron/js2c/browser_init:2:84019)\n    at WebContents.emit (node:events:519:28)\n    at WebContents.emit (node:domain:488:12)\n    at emitter.emit (/nix/store/f3x3snsnjnfzg12g7586syg5cyn8sgph-discord-0.0.58/opt/Discord/resources/app.asar/node_modules/@sentry/electron/main/integrations/electron-breadcrumbs.js:116:20)"},{"timestamp":1720369272.432,"category":"console","level":"log","message":"mainScreen.UpdaterEvents: CHECK_FOR_UPDATES UPDATE_NOT_AVAILABLE"},{"timestamp":1720369272.432,"category":"console","level":"log","message":"2024-07-07T16:21:12.432Z [Modules] Host is up to date."},{"timestamp":1720369272.432,"category":"console","level":"log","message":"2024-07-07T16:21:12.432Z [Modules] Checking for module updates at https://discord.com/api/modules/stable/versions.json"},{"timestamp":1720369272.436,"type":"http","category":"electron.net","data":{"url":"https://discord.com/api/modules/stable/versions.json?host_version=0.0.58&platform=linux&_=5734564","method":"GET","status_code":200}},{"timestamp":1720369272.436,"category":"console","level":"log","message":"2024-07-07T16:21:12.436Z [Modules] No module updates available."},{"timestamp":1720369272.437,"category":"console","level":"log","message":"legacyModuleUpdater: update-check-finished"},{"timestamp":1720369272.534,"category":"console","level":"log","message":"legacyModuleUpdater: installed-module discord_rpc 1 1 true"},{"timestamp":1720369272.582,"category":"console","level":"log","message":"mainScreen.UpdaterEvents: UPDATER_HISTORY_QUERY_AND_TRUNCATE"},{"timestamp":1720369272.731,"category":"electron","message":"window.show","type":"ui","data":{"id":2,"url":"https://discord.com/login","title":""}},{"timestamp":1720369284.341,"category":"ui.click","message":"input#uid_17.inputDefault_f8bc55.input_f8bc55.inputField_cc6ddd[aria-label=\"Email or Phone Number\"][type=\"text\"][name=\"email\"]"},{"timestamp":1720369322.507,"category":"electron","message":"window.enter-full-screen","type":"ui","data":{"id":2,"url":"https://discord.com/channels/@me"}},{"timestamp":1720369375.65,"category":"electron","message":"window.leave-full-screen","type":"ui","data":{"id":2,"url":"https://discord.com/channels/@me"}},{"timestamp":1720369377.23,"category":"ui.click","message":"div.layerContainer_cd0de5 > div.backdrop_e4f2ae.withLayer_e4f2ae"},{"timestamp":1720369379.139,"category":"ui.click","message":"button.button_f67531.enabled_f67531.button_dd4f85.lookBlank_dd4f85.colorBrand_dd4f85.grow_dd4f85.button_f67531[aria-label=\"User Settings\"][type=\"button\"]"},{"timestamp":1720369385.237,"category":"ui.click","message":"div.bd-themes-tab.item_a0.selected_a0.themed_a0"},{"timestamp":1720369402.881,"category":"electron","message":"window.blur","type":"ui","data":{"id":2,"url":"https://discord.com/channels/@me"}},{"timestamp":1720369402.881,"category":"electron","message":"app.browser-window-blur","type":"ui"},{"timestamp":1720369552.69,"category":"electron","message":"window.focus","type":"ui","data":{"id":2,"url":"https://discord.com/channels/@me"}},{"timestamp":1720369552.69,"category":"electron","message":"app.browser-window-focus","type":"ui"},{"timestamp":1720369559.994,"category":"ui.click","message":"div.bd-addon-header > div.bd-switch.bd-switch-checked > input[type=\"checkbox\"]"},{"timestamp":1720369561.127,"category":"ui.click","message":"div.bd-addon-header > div.bd-switch.bd-switch-checked > input[type=\"checkbox\"]"},{"timestamp":1720369563.269,"category":"ui.click","message":"div.container_df5532 > div.closeButton_df5532[aria-label=\"Close\"] > svg"},{"timestamp":1720369571.701,"category":"ui.click","message":"a.link_c91bad[aria-label=\"unread, Tyson❤ (direct message)\"]"},{"timestamp":1720369575.355,"category":"ui.click","message":"div"},{"timestamp":1720369579.79,"category":"ui.input","message":"div.markup_f8f345.editor_a552a6.slateTextArea_e52116.fontSize16Padding_d0696b[aria-label=\"Message @Tyson❤\"]"},{"timestamp":1720369580.358,"category":"console","level":"log","message":"legacyModuleUpdater: installed-module discord_spellcheck 1 1 true"},{"timestamp":1720369580.359,"category":"console","level":"log","message":"mainScreen.UpdaterEvents: UPDATER_HISTORY_QUERY_AND_TRUNCATE"},{"timestamp":1720369584.444,"category":"ui.input","message":"div.markup_f8f345.editor_a552a6.slateTextArea_e52116.fontSize16Padding_d0696b[aria-label=\"Message @Tyson❤\"]"},{"timestamp":1720369598.931,"category":"ui.click","message":"div.activity_c91bad.subtext_c91bad > div.activityText_c91bad"},{"timestamp":1720369608.501,"category":"ui.click","message":"a.link_c91bad[aria-label=\"Tyson❤ (direct message)\"] > div.layout_f9647d"},{"timestamp":1720369612.059,"category":"electron","message":"window.blur","type":"ui","data":{"id":2,"url":"https://discord.com/channels/@me/315224626886213642"}},{"timestamp":1720369612.059,"category":"electron","message":"app.browser-window-blur","type":"ui"}],"_attachments":[],"_user":{"id":"200223174565167105","username":"wyd.noelle","email":"ppg0291@gmail.com"},"_tags":{"nativeBuildNumber":"null"},"_extra":{},"_contexts":{},"_sdkProcessingMetadata":{},"_propagationContext":{"traceId":"c7bb065175f4402caad2b9178fc4d3b8","spanId":"88f281e0c8832a18"}},"event":{"sdk":{"name":"sentry.javascript.electron","packages":[{"name":"npm:@sentry/electron","version":"4.13.0"}],"version":"4.13.0"},"contexts":{"app":{"app_name":"discord","app_version":"0.0.58","app_start_time":"2024-07-07T16:21:06.350Z"},"os":{"kernel_version":"5.15.153.1-microsoft-standard-WSL2+","name":"Ubuntu Linux","version":"\"24.05\""},"browser":{"name":"Chrome"},"chrome":{"name":"Chrome","type":"runtime","version":"124.0.6367.243"},"device":{"arch":"x64","family":"Desktop"},"node":{"name":"Node","type":"runtime","version":"20.14.0"},"runtime":{"name":"Electron","version":"30.1.0"}},"environment":"stable","release":"0.0.58","user":{"ip_address":"{{auto}}"},"tags":{"event.origin":"electron","event.environment":"javascript","event.process":"browser","event_type":"javascript"}}}